citeurl/__init__.py
citeurl/authority.py
citeurl/citation.py
citeurl/citator.py
citeurl/cli.py
citeurl/mdx.py
citeurl/regex_mods.py
citeurl/tokens.py
citeurl/templates/caselaw.yaml
citeurl/templates/general federal law.yaml
citeurl/templates/secondary sources.yaml
citeurl/templates/specific federal laws.yaml
citeurl/templates/state law.yaml
citeurl/web/__init__.py
citeurl/web/citeurl.js
citeurl/web/logo.svg
citeurl/web/makejs.py
citeurl/web/resources.py
citeurl/web/server.py
citeurl/web/style.css
citeurl-12.0.3.dist-info/licenses/LICENSE.md
tests/__init__.py
tests/_test_links.py
tests/test_core.py
tests/test_js.py
tests/test_mdx.py
tests/test_templates.py
citeurl-12.0.3.dist-info/METADATA
citeurl-12.0.3.dist-info/WHEEL
citeurl-12.0.3.dist-info/entry_points.txt
citeurl-12.0.3.dist-info/top_level.txt
citeurl-12.0.3.dist-info/RECORD
