Metadata-Version: 2.4
Name: citeurl
Version: 12.0.3
Summary: an extensible tool to process legal citations in text
Home-page: https://raindrum.github.io/citeurl
Author: Simon Raindrum Sherred
Author-email: simonraindrum@gmail.com
License: MIT
Classifier: Development Status :: 5 - Production/Stable
Classifier: Intended Audience :: Legal Industry
Classifier: Programming Language :: Python :: 3.9
Classifier: License :: OSI Approved :: MIT License
Classifier: Operating System :: OS Independent
Classifier: Topic :: Text Processing :: Filters
Classifier: Topic :: Text Processing :: Markup :: HTML
Classifier: Topic :: Text Processing :: Markup :: Markdown
Classifier: Topic :: Internet :: WWW/HTTP :: WSGI :: Application
Classifier: Topic :: Software Development :: Libraries :: Python Modules
License-File: LICENSE.md
Requires-Dist: pyyaml
Provides-Extra: web
Requires-Dist: flask; extra == "web"
Requires-Dist: gevent; extra == "web"
Provides-Extra: config
Requires-Dist: appdirs; extra == "config"
Provides-Extra: full
Requires-Dist: flask; extra == "full"
Requires-Dist: gevent; extra == "full"
Requires-Dist: appdirs; extra == "full"
Dynamic: author
Dynamic: author-email
Dynamic: classifier
Dynamic: description
Dynamic: description-content-type
Dynamic: home-page
Dynamic: license
Dynamic: license-file
Dynamic: provides-extra
Dynamic: requires-dist
Dynamic: summary
